konviktion/__init__.py
konviktion/deployed.py
konviktion/deployments/test/configs/config.yaml
konviktion/deployments/test/docker-compose.yml
konviktion/errors.py
konviktion/funcs.py
konviktion/konviktion.py
konviktion/rath.py
konviktion/structures.py
konviktion-0.1.0.dist-info/METADATA
konviktion-0.1.0.dist-info/WHEEL
konviktion-0.1.0.dist-info/RECORD
