Metadata-Version: 2.1
Name: konviktion
Version: 0.1.0
Summary: 
Author: jhnnsrs
Author-email: jhnnsrs@gmail.com
Requires-Python: >=3.9,<4.0
Classifier: Programming Language :: Python :: 3
Classifier: Programming Language :: Python :: 3.9
Classifier: Programming Language :: Python :: 3.10
Classifier: Programming Language :: Python :: 3.11
Requires-Dist: dokker (>=0.1.25)
Requires-Dist: rath[websockets] (>=0.5.0)
